LICENSE
README.md
pyproject.toml
setup.py
damescikit/runtests.sh
damescikit.egg-info/PKG-INFO
damescikit.egg-info/SOURCES.txt
damescikit.egg-info/dependency_links.txt
damescikit.egg-info/entry_points.txt
damescikit.egg-info/not-zip-safe
damescikit.egg-info/requires.txt
damescikit.egg-info/top_level.txt
damescikit/tests/__init__.py
damescikit/tests/test_models.py
damescikit/tests/test_vectorizer.py